webarchiver/__init__.py
webarchiver/version.py
webarchiver/webarchiver.py
webarchiver/lib/uBlock-Origin_v1.27.0.crx
webarchiver-0.32.6.data/data/webarchiver/uBlock-Origin_v1.27.0.crx
webarchiver-0.32.6.dist-info/LICENSE
webarchiver-0.32.6.dist-info/METADATA
webarchiver-0.32.6.dist-info/WHEEL
webarchiver-0.32.6.dist-info/entry_points.txt
webarchiver-0.32.6.dist-info/top_level.txt
webarchiver-0.32.6.dist-info/RECORD
