Metadata-Version: 2.1
Name: webarchiver
Version: 0.32.6
Summary: Python tool that allows you to take multiple full page screenshots of web pages without ads.
Home-page: https://github.com/Knuckles-Team/webarchiver
Author: Audel Rouhi
Author-email: knucklessg1@gmail.com
License: MIT
Platform: UNKNOWN
Classifier: Development Status :: 5 - Production/Stable
Classifier: License :: Public Domain
Classifier: Environment :: Console
Classifier: Operating System :: POSIX :: Linux
Classifier: Programming Language :: Python :: 3.8
Classifier: Programming Language :: Python :: 3.9
Classifier: Programming Language :: Python :: 3.10
Classifier: Programming Language :: Python :: 3.11
Classifier: Programming Language :: Python :: 3.12
License-File: LICENSE
Requires-Dist: Pillow (>=10.2.0)
Requires-Dist: beautifulsoup4 (>=4.12.3)
Requires-Dist: piexif (>=1.1.3)
Requires-Dist: selenium (>=4.17.2)
Requires-Dist: webdriver-manager (>=4.0.1)
